MANIFEST.in
README.md
meta.json
setup.py
xx_ner_demo/__init__.py
xx_ner_demo/meta.json
xx_ner_demo.egg-info/PKG-INFO
xx_ner_demo.egg-info/SOURCES.txt
xx_ner_demo.egg-info/dependency_links.txt
xx_ner_demo.egg-info/entry_points.txt
xx_ner_demo.egg-info/not-zip-safe
xx_ner_demo.egg-info/requires.txt
xx_ner_demo.egg-info/top_level.txt
xx_ner_demo/xx_ner_demo-0.0.0/README.md
xx_ner_demo/xx_ner_demo-0.0.0/config.cfg
xx_ner_demo/xx_ner_demo-0.0.0/meta.json
xx_ner_demo/xx_ner_demo-0.0.0/tokenizer
xx_ner_demo/xx_ner_demo-0.0.0/ner/cfg
xx_ner_demo/xx_ner_demo-0.0.0/ner/model
xx_ner_demo/xx_ner_demo-0.0.0/ner/moves
xx_ner_demo/xx_ner_demo-0.0.0/tok2vec/cfg
xx_ner_demo/xx_ner_demo-0.0.0/tok2vec/model
xx_ner_demo/xx_ner_demo-0.0.0/vocab/key2row
xx_ner_demo/xx_ner_demo-0.0.0/vocab/lookups.bin
xx_ner_demo/xx_ner_demo-0.0.0/vocab/strings.json
xx_ner_demo/xx_ner_demo-0.0.0/vocab/vectors
xx_ner_demo/xx_ner_demo-0.0.0/vocab/vectors.cfg