Metadata-Version: 2.1
Name: xx-ner-demo
Version: 0.0.0
Summary: UNKNOWN
Home-page: UNKNOWN
Author: 
Author-email: 
License: UNKNOWN
Platform: UNKNOWN
